strands_nvidia_nim/__init__.py
strands_nvidia_nim/provider.py
strands_nvidia_nim-1.0.0.dist-info/licenses/LICENSE
strands_nvidia_nim-1.0.0.dist-info/METADATA
strands_nvidia_nim-1.0.0.dist-info/WHEEL
strands_nvidia_nim-1.0.0.dist-info/top_level.txt
strands_nvidia_nim-1.0.0.dist-info/RECORD
