Metadata-Version: 2.4
Name: strands-nvidia-nim
Version: 1.0.0
Summary: Nvidia NIM provider for Strands Agents SDK
Home-page: https://github.com/thiago4go/strands-nvidia-nim
Author: Thiago S Shimada Ramos
Author-email: Your Name <your.email@example.com>
License: MIT
Project-URL: Homepage, https://github.com/yourusername/strands-nvidia-nim
Project-URL: Repository, https://github.com/yourusername/strands-nvidia-nim
Project-URL: Issues, https://github.com/yourusername/strands-nvidia-nim/issues
Project-URL: Documentation, https://github.com/yourusername/strands-nvidia-nim#readme
Keywords: strands,nvidia,nim,llm,ai,agents
Classifier: Development Status :: 4 - Beta
Classifier: Intended Audience :: Developers
Classifier: License :: OSI Approved :: MIT License
Classifier: Operating System :: OS Independent
Classifier: Programming Language :: Python :: 3
Classifier: Programming Language :: Python :: 3.8
Classifier: Programming Language :: Python :: 3.9
Classifier: Programming Language :: Python :: 3.10
Classifier: Programming Language :: Python :: 3.11
Requires-Python: >=3.8
License-File: LICENSE
Requires-Dist: strands>=0.1.0
Requires-Dist: litellm>=1.0.0
Requires-Dist: typing-extensions>=4.0.0
Provides-Extra: dev
Requires-Dist: pytest>=6.0; extra == "dev"
Requires-Dist: black>=22.0; extra == "dev"
Requires-Dist: flake8>=4.0; extra == "dev"
Requires-Dist: mypy>=0.900; extra == "dev"
Dynamic: author
Dynamic: home-page
Dynamic: license-file
Dynamic: requires-python
